quranallsbuforuni/__init__.py
quranallsbuforuni/module1.py
quranallsbuforuni/module2.py
quranerabdar-1.dist-info/METADATA
quranerabdar-1.dist-info/WHEEL
quranerabdar-1.dist-info/top_level.txt
quranerabdar-1.dist-info/RECORD
