Metadata-Version: 2.1
Name: quranerabdar
Version: 1
Summary: Quranerabdar
Author: Masoud Shafiei
Author-email: masoudshafiei89@yahoo.com
Keywords: quran,sbu
Classifier: Programming Language :: Python :: 3
